pondpy/__init__.py
pondpy/analysis/__init__.py
pondpy/analysis/fem_analysis.py
pondpy/analysis/pond_analysis.py
pondpy/design/__init__.py
pondpy/design/steel_beam_design.py
pondpy/design/steel_joist_design.py
pondpy/pondpy.py
pondpy/report/__init__.py
pondpy/report/helpers/__init__.py
pondpy/report/helpers/generate_pdf.py
pondpy/report/helpers/get_version_from_pyproject.py
pondpy/report/helpers/render_html.py
pondpy/report/helpers/save_figures.py
pondpy/report/report_builder.py
pondpy/report/templates/favicon.ico
pondpy/report/templates/pondpy.svg
pondpy/report/templates/report_template.html
pondpy-0.2.3.dist-info/LICENSE
pondpy-0.2.3.dist-info/METADATA
pondpy-0.2.3.dist-info/WHEEL
pondpy-0.2.3.dist-info/RECORD
