Metadata-Version: 2.1
Name: pondpy
Version: 0.2.3
Summary: Package to aid in the design of low-slope roof systems for ponding stability and impounded rain load.
License: MIT
Author: Matthew Upshaw
Author-email: matthew.upshaw02@gmail.com
Requires-Python: >=3.10,<4.0
Classifier: License :: OSI Approved :: MIT License
Classifier: Programming Language :: Python :: 3
Classifier: Programming Language :: Python :: 3.10
Classifier: Programming Language :: Python :: 3.11
Classifier: Programming Language :: Python :: 3.12
Requires-Dist: joistpy (==1.1.0)
Requires-Dist: matplotlib (==3.9.0)
Requires-Dist: numpy (==1.26.4)
Requires-Dist: scipy (==1.13.1)
Requires-Dist: steelpy (==1.1.1)
Requires-Dist: toml (==0.10.2)
